django_croppic_py3/__init__.py
django_croppic_py3/admin.py
django_croppic_py3/conf.py
django_croppic_py3/forms.py
django_croppic_py3/models.py
django_croppic_py3/tests.py
django_croppic_py3/urls.py
django_croppic_py3/utils.py
django_croppic_py3/views.py
django_croppic_py3/migrations/__init__.py
django_croppic_py3-0.0.2.dist-info/METADATA
django_croppic_py3-0.0.2.dist-info/RECORD
django_croppic_py3-0.0.2.dist-info/WHEEL
django_croppic_py3-0.0.2.dist-info/top_level.txt
