Metadata-Version: 2.1
Name: django-croppic-py3
Version: 0.0.2
Summary: A version of the django-croppic module updated to work with django 2+ and Python 3+.
Home-page: https://mooloomedia.com
Author: Alex Davies
Author-email: alex@mooloomedia.com
License: UNKNOWN
Platform: UNKNOWN
Classifier: Programming Language :: Python :: 3
Classifier: License :: OSI Approved :: MIT License
Classifier: Operating System :: OS Independent
